puter/__init__.py
puter/ai.py
puter/available_models.json
puter/config.py
puter/exceptions.py
puter_python_sdk-0.5.0.dist-info/METADATA
puter_python_sdk-0.5.0.dist-info/WHEEL
puter_python_sdk-0.5.0.dist-info/license.md
puter_python_sdk-0.5.0.dist-info/top_level.txt
puter_python_sdk-0.5.0.dist-info/RECORD
