Metadata-Version: 2.1
Name: puter-python-sdk
Version: 0.5.0
Summary: Python SDK for accessing free AI models through Puter.js
Home-page: https://github.com/CuzImSlymi/puter-python-sdk
Author: Slymi
Author-email: Slymi <justin@slymi.org>
License: MIT
Project-URL: Homepage, https://github.com/CuzImSlymi/puter-python-sdk
Project-URL: Repository, https://github.com/CuzImSlymi/puter-python-sdk
Project-URL: Issues, https://github.com/CuzImSlymi/puter-python-sdk/issues
Keywords: ai,puter,sdk,chatbot,api
Classifier: Development Status :: 4 - Beta
Classifier: Intended Audience :: Developers
Classifier: Operating System :: OS Independent
Classifier: Programming Language :: Python :: 3
Classifier: Programming Language :: Python :: 3.7
Classifier: Programming Language :: Python :: 3.8
Classifier: Programming Language :: Python :: 3.9
Classifier: Programming Language :: Python :: 3.10
Classifier: Programming Language :: Python :: 3.11
Classifier: Programming Language :: Python :: 3.12
Classifier: Topic :: Software Development :: Libraries :: Python Modules
Classifier: Topic :: Scientific/Engineering :: Artificial Intelligence
Requires-Python: >=3.7
License-File: license.md
Requires-Dist: requests>=2.25.0
Requires-Dist: aiohttp>=3.8.0
Requires-Dist: asyncio-throttle>=1.0.2
Provides-Extra: dev
Requires-Dist: pytest>=6.0; extra == "dev"
Requires-Dist: pytest-cov; extra == "dev"
Requires-Dist: pytest-asyncio; extra == "dev"
Requires-Dist: black; extra == "dev"
Requires-Dist: flake8; extra == "dev"
Requires-Dist: mypy; extra == "dev"
Requires-Dist: types-requests>=2.31.0; extra == "dev"
